{
  "source": "bilibili",
  "generated_at": "2025-11-26 12:40:04 GMT",
  "items": [
    {
      "rank": 1,
      "text": "香港火灾升至五级",
      "mark": "http://i0.hdslb.com/bfs/activity-plat/static/20221118/eaf2dd702d7cc14d8d9511190245d057/UF7B1wVKT2.png"
    },
    {
      "rank": 2,
      "text": "厂长卸任JDG主教练",
      "mark": null
    },
    {
      "rank": 3,
      "text": "俄乌和平计划是谁起草的",
      "mark": "http://i0.hdslb.com/bfs/activity-plat/static/20221118/eaf2dd702d7cc14d8d9511190245d057/UF7B1wVKT2.png"
    },
    {
      "rank": 4,
      "text": "玄界之门",
      "mark": "http://i0.hdslb.com/bfs/activity-plat/static/20240304/fbb6ffcfd09815bd66290b6b7bde1196/OBQYPHMTcv.png"
    },
    {
      "rank": 5,
      "text": "鸣潮3.0卫星角色爆料",
      "mark": null
    },
    {
      "rank": 6,
      "text": "外交部称日方所谓立场未变是远远不够的",
      "mark": null
    },
    {
      "rank": 7,
      "text": "开展学术不端撤稿论文专项整治",
      "mark": null
    },
    {
      "rank": 8,
      "text": "1元胡辣汤味道如何",
      "mark": "http://i0.hdslb.com/bfs/activity-plat/static/20221118/eaf2dd702d7cc14d8d9511190245d057/UF7B1wVKT2.png"
    },
    {
      "rank": 9,
      "text": "原神杜林综合测评",
      "mark": null
    },
    {
      "rank": 10,
      "text": "零点场速评疯狂动物城2",
      "mark": null
    }
  ]
}