{
  "source": "bilibili",
  "generated_at": "2025-11-08 02:35:03 GMT",
  "items": [
    {
      "rank": 1,
      "text": "管泽元S15决赛纯分析",
      "mark": "http://i0.hdslb.com/bfs/activity-plat/static/20221118/eaf2dd702d7cc14d8d9511190245d057/UF7B1wVKT2.png"
    },
    {
      "rank": 2,
      "text": "卢浮宫百年盗窃案史梳理",
      "mark": "http://i0.hdslb.com/bfs/activity-plat/static/20221118/eaf2dd702d7cc14d8d9511190245d057/UF7B1wVKT2.png"
    },
    {
      "rank": 3,
      "text": "新世纪神鹰战士",
      "mark": "http://i0.hdslb.com/bfs/activity-plat/static/20221117/eaf2dd702d7cc14d8d9511190245d057/EeuqbMwao9.png"
    },
    {
      "rank": 4,
      "text": "周深造物舞台超强爆发力",
      "mark": null
    },
    {
      "rank": 5,
      "text": "福建舰入列有何战略意义",
      "mark": "http://i0.hdslb.com/bfs/activity-plat/static/20221213/eaf2dd702d7cc14d8d9511190245d057/lrx9rnKo24.png"
    },
    {
      "rank": 6,
      "text": "谁还有多余资金是什么梗",
      "mark": null
    },
    {
      "rank": 7,
      "text": "Doran谈Oner生死局选蒙多",
      "mark": null
    },
    {
      "rank": 8,
      "text": "张韶涵昔涟MV上线",
      "mark": null
    },
    {
      "rank": 9,
      "text": "用卫星跟踪一座垃圾山的消失",
      "mark": null
    },
    {
      "rank": 10,
      "text": "福建舰高清大图来了",
      "mark": null
    }
  ]
}