{
  "source": "bilibili",
  "generated_at": "2025-10-18 02:30:04 GMT",
  "items": [
    {
      "rank": 1,
      "text": "瑞士轮第三日赛后锐评",
      "mark": "http://i0.hdslb.com/bfs/activity-plat/static/20221118/eaf2dd702d7cc14d8d9511190245d057/UF7B1wVKT2.png"
    },
    {
      "rank": 2,
      "text": "把家门改造成了屏幕",
      "mark": "http://i0.hdslb.com/bfs/activity-plat/static/20221118/eaf2dd702d7cc14d8d9511190245d057/UF7B1wVKT2.png"
    },
    {
      "rank": 3,
      "text": "给猫咪小镇造了地下宫殿",
      "mark": "http://i0.hdslb.com/bfs/activity-plat/static/20221213/eaf2dd702d7cc14d8d9511190245d057/lrx9rnKo24.png"
    },
    {
      "rank": 4,
      "text": "大雪暴雨南下",
      "mark": "http://i0.hdslb.com/bfs/activity-plat/static/20221213/eaf2dd702d7cc14d8d9511190245d057/lrx9rnKo24.png"
    },
    {
      "rank": 5,
      "text": "人民币的设计有多牛",
      "mark": null
    },
    {
      "rank": 6,
      "text": "锐评TES为何不敌KT",
      "mark": null
    },
    {
      "rank": 7,
      "text": "6步链接全球人口是真的吗",
      "mark": "http://i0.hdslb.com/bfs/activity-plat/static/20221118/eaf2dd702d7cc14d8d9511190245d057/UF7B1wVKT2.png"
    },
    {
      "rank": 8,
      "text": "圣枪哥挖掘机游龙三杀",
      "mark": null
    },
    {
      "rank": 9,
      "text": "在米哈游楼下唱土龙吟",
      "mark": null
    },
    {
      "rank": 10,
      "text": "美俄匈牙利会晤有何看点",
      "mark": null
    }
  ]
}